scaneo/api.py
scaneo/main.py
scaneo/routers/annotations.py
scaneo/routers/campaigns.py
scaneo/routers/geojson.py
scaneo/routers/images.py
scaneo/routers/labels.py
scaneo/routers/models.py
scaneo/routers/plugins.py
scaneo/src/__init__.py
scaneo/src/errors/__init__.py
scaneo/src/errors/campaigns.py
scaneo/src/errors/labels.py
scaneo/src/models/__init__.py
scaneo/src/models/annotation.py
scaneo/src/models/campaign.py
scaneo/src/models/image.py
scaneo/src/models/label.py
scaneo/src/models/model.py
scaneo/src/models/plugin.py
scaneo/src/repos/AnnotationsDBRepo.py
scaneo/src/repos/CampaignsDBRepo.py
scaneo/src/repos/DBRepo.py
scaneo/src/repos/EOTDLRepo.py
scaneo/src/repos/ImagesDBRepo.py
scaneo/src/repos/LabelMappingsDBRepo.py
scaneo/src/repos/LabelsDBRepo.py
scaneo/src/repos/ModelsDBRepo.py
scaneo/src/repos/PluginsDBRepo.py
scaneo/src/repos/__init__.py
scaneo/src/usecases/__init__.py
scaneo/src/usecases/annotations/__init__.py
scaneo/src/usecases/annotations/create_classification_annotation.py
scaneo/src/usecases/annotations/create_detection_annotation.py
scaneo/src/usecases/annotations/create_points_annotation.py
scaneo/src/usecases/annotations/create_segmentation_annotation.py
scaneo/src/usecases/annotations/delete_annotation.py
scaneo/src/usecases/annotations/export_annotations.py
scaneo/src/usecases/annotations/increment_annotation_counter.py
scaneo/src/usecases/annotations/retrieve_annotations.py
scaneo/src/usecases/annotations/update_detection_annotation.py
scaneo/src/usecases/annotations/update_points_annotation.py
scaneo/src/usecases/campaigns/__init__.py
scaneo/src/usecases/campaigns/create_campaign.py
scaneo/src/usecases/campaigns/create_campaign_eotdl.py
scaneo/src/usecases/campaigns/create_imported_campaign.py
scaneo/src/usecases/campaigns/delete_campaign.py
scaneo/src/usecases/campaigns/export_campaign.py
scaneo/src/usecases/campaigns/retrieve_campaign_label_mappings.py
scaneo/src/usecases/campaigns/retrieve_campaigns.py
scaneo-2025.6.23.dist-info/METADATA
scaneo-2025.6.23.dist-info/WHEEL
scaneo-2025.6.23.dist-info/entry_points.txt
scaneo-2025.6.23.dist-info/licenses/LICENSE
scaneo-2025.6.23.dist-info/RECORD
