Metadata-Version: 2.4
Name: scaneo
Version: 2025.6.23
Summary: A labelling tool for satellite imagery
Author-email: earthpulse <it@earthpulse.es>
License-File: LICENSE
Requires-Python: >=3.12
Requires-Dist: cachetools>=5.3.1
Requires-Dist: fastapi>=0.90.0
Requires-Dist: matplotlib>=3.4.3
Requires-Dist: mercantile>=1.2.1
Requires-Dist: pyproj>=3.7.1
Requires-Dist: python-dotenv>=1.0.1
Requires-Dist: rasterio>=1.2.0
Requires-Dist: requests>=2.32.3
Requires-Dist: shapely>=1.7.1
Requires-Dist: tqdm>=4.62.3
Requires-Dist: typer>=0.9.0
Requires-Dist: uvicorn[standard]>=0.22.0
